pyiron_workflow_atomistics/__init__.py
pyiron_workflow_atomistics/_version.py
pyiron_workflow_atomistics/ase_calculator.py
pyiron_workflow_atomistics/ase_engine.py
pyiron_workflow_atomistics/bulk.py
pyiron_workflow_atomistics/calculator.py
pyiron_workflow_atomistics/dataclass_storage.py
pyiron_workflow_atomistics/featurisers.py
pyiron_workflow_atomistics/utils.py
pyiron_workflow_atomistics/gb/__init__.py
pyiron_workflow_atomistics/gb/analysis.py
pyiron_workflow_atomistics/gb/cleavage.py
pyiron_workflow_atomistics/gb/dataclass_storage.py
pyiron_workflow_atomistics/gb/gb_study.py
pyiron_workflow_atomistics/gb/hcp_generator.py
pyiron_workflow_atomistics/gb/optimiser.py
pyiron_workflow_atomistics/gb/segregation.py
pyiron_workflow_atomistics/gb/utils.py
pyiron_workflow_atomistics/gb/gb_code/__init__.py
pyiron_workflow_atomistics/gb/gb_code/constructor.py
pyiron_workflow_atomistics/gb/gb_code/csl_generator.py
pyiron_workflow_atomistics/gb/gb_code/gb_generator.py
pyiron_workflow_atomistics/gb/gb_code/searcher.py
pyiron_workflow_atomistics/pyiron_module_template/__init__.py
pyiron_workflow_atomistics/pyiron_module_template/_version.py
pyiron_workflow_atomistics/structure_manipulator/__init__.py
pyiron_workflow_atomistics/structure_manipulator/interstitials.py
pyiron_workflow_atomistics/structure_manipulator/tools.py
pyiron_workflow_atomistics-0.0.2.dist-info/licenses/LICENSE
pyiron_workflow_atomistics-0.0.2.dist-info/METADATA
pyiron_workflow_atomistics-0.0.2.dist-info/WHEEL
pyiron_workflow_atomistics-0.0.2.dist-info/top_level.txt
pyiron_workflow_atomistics-0.0.2.dist-info/RECORD
