Metadata-Version: 2.4
Name: pyiron_workflow_atomistics
Version: 0.0.2
Summary: A pyiron module for atomistic simulation workflows
Author-email: pyiron team <pyiron@mpie.de>
License: BSD 3-Clause License
Project-URL: Homepage, https://pyiron.org/
Project-URL: Documentation, https://pyiron_workflow_atomistics.readthedocs.io
Project-URL: Repository, https://github.com/pyiron/pyiron_workflow_atomistics
Keywords: pyiron,atomistics,workflow
Classifier: Development Status :: 3 - Alpha
Classifier: Topic :: Scientific/Engineering
Classifier: License :: OSI Approved :: BSD License
Classifier: Intended Audience :: Science/Research
Classifier: Operating System :: OS Independent
Classifier: Programming Language :: Python :: 3.9
Classifier: Programming Language :: Python :: 3.10
Classifier: Programming Language :: Python :: 3.11
Classifier: Programming Language :: Python :: 3.12
Requires-Python: <3.14,>=3.9
License-File: LICENSE
Requires-Dist: numpy<1.27.0,>=1.22.0
Requires-Dist: pandas<2.4.0,>=1.3.0
Requires-Dist: matplotlib<3.11.0,>=3.10.6
Requires-Dist: ase<3.27.0,>=3.21.0
Requires-Dist: scipy<1.17.0,>=1.4.0
Requires-Dist: pyiron-workflow<=0.15.2,>=0.14.1
Requires-Dist: pymatgen<2025.7.0,>=2024.8.8
Requires-Dist: pyiron_snippets<=0.2.0,>=0.1.0
Requires-Dist: scikit-learn<1.8.0,>=1.0.0
Dynamic: license-file
